{
  "type": "minecraft:chests",
  "pools": [
    {
      "rolls": {
        "min": 1,
        "max": 5
      },
      "entries": [
        {
          "type": "minecraft:item",
          "weight": 1,
          "name": "mna:torn_journal_page"
        }
      ],
      "functions": [
        {
          "function": "mna:random_journal_page"
        }
      ],
      "conditions": [
        {
          "condition": "minecraft:random_chance",
          "chance": 0.35
        }
      ]
    },
    {
      "rolls": 1,
      "entries": [
        {
          "type": "minecraft:tag",
          "name": "mna:relics",
          "expand": true,
          "weight": 1
        },
        {
          "type": "minecraft:item",
          "name": "mna:spell",
          "weight": 1,
          "functions": [
            {
              "function": "mna:random_artifact_spell"
            }
          ]
        }
      ],
      "conditions": [
        {
          "condition": "minecraft:random_chance",
          "chance": 0.01
        }
      ]
    },
    {
      "rolls": 1,
      "entries": [
        {
          "type": "minecraft:tag",
          "name": "arcado:ancient_curios",
          "expand": true,
          "weight": 1
        }
      ],
      "conditions": [
        {
          "condition": "minecraft:random_chance",
          "chance": 0.01
        }
      ]
    },
    {
      "rolls": {
        "min": 0,
        "max": 4
      },
      "entries": [
        {
          "type": "minecraft:tag",
          "name": "arcado:ancient_curios",
          "expand": true,
          "weight": 1,
          "conditions": [
            {
              "condition": "minecraft:random_chance",
              "chance": 0.25
            }
          ]
        },
        {
          "type": "minecraft:item",
          "name": "minecraft:iron_nugget",
          "weight": 1,
          "functions": [
            {
              "function": "minecraft:set_count",
              "count": {
                "min": 4,
                "max": 18
              }
            }
          ]
        },
        {
          "type": "minecraft:item",
          "name": "minecraft:gold_nugget",
          "weight": 1,
          "functions": [
            {
              "function": "minecraft:set_count",
              "count": {
                "min": 4,
                "max": 18
              }
            }
          ]
        },
        {
          "type": "minecraft:item",
          "name": "minecraft:diamond",
          "weight": 1,
          "conditions": [
            {
              "condition": "minecraft:random_chance",
              "chance": 0.5
            }
          ]
        },
        {
          "type": "minecraft:item",
          "name": "minecraft:bell",
          "weight": 1,
          "conditions": [
            {
              "condition": "minecraft:random_chance",
              "chance": 0.1
            }
          ]
        }
      ]
    },
    {
      "rolls": {
        "min": 1,
        "max": 4
      },
      "entries": [
        {
          "type": "minecraft:item",
          "weight": 3,
          "name": "mna:chimerite_gem",
          "functions": [
            {
              "function": "minecraft:set_count",
              "count": {
                "min": 1,
                "max": 3
              }
            }
          ],
          "conditions": [
            {
              "condition": "minecraft:random_chance",
              "chance": 0.5
            }
          ]
        },
        {
          "type": "minecraft:item",
          "weight": 10,
          "name": "mna:vinteum_dust",
          "functions": [
            {
              "function": "minecraft:set_count",
              "count": {
                "min": 2,
                "max": 5
              }
            }
          ],
          "conditions": [
            {
              "condition": "minecraft:random_chance",
              "chance": 0.5
            }
          ]
        }
      ]
    }
  ]
}
