{
  "type": "forge:conditional",
  "recipes": [
    {
      "conditions": [
        {
          "type": "forge:mod_loaded",
          "modid": "magichem"
        }
      ],
      "recipe": {
        "type": "mna:eldrin-altar",
        "output": "arcado:bracelet_tourmaline_4_electrum",
        "tier": 4,
        "items": [
          "arcado:bracelet_tourmaline_3_electrum",
          "magichem:perfected_electrum",
          "mna:mote_water",
          "minecraft:diamond",
          "arcado:preeminent_polish",
          "minecraft:diamond",
          "magichem:mote_achromatic",
          "magichem:perfected_electrum",
          "arcado:jewel_tourmaline"
        ],
        "power_requirements": [
          {
            "affinity": "WATER",
            "amount": 720
          }
        ],
        "colors": [
          12430444,
          1261470
        ]
      }
    }
  ]
}
